MANIFEST.in
README.rst
setup.py
bin/QuadWriteToSharedMem
bin/ReadFromQuadSharedMem
quadwi/QuadSharedMemIf.py
quadwi/QuadSharedMemReader.py
quadwi/QuadSharedMemWriter.py
quadwi/QuadUdpDataSource.py
quadwi/__init__.py
quadwi/quad_mem_map
quadwi.egg-info/PKG-INFO
quadwi.egg-info/SOURCES.txt
quadwi.egg-info/dependency_links.txt
quadwi.egg-info/not-zip-safe
quadwi.egg-info/requires.txt
quadwi.egg-info/top_level.txt