Metadata-Version: 1.1
Name: quadwi
Version: 0.1
Summary: Python package containing a wireless communication API to be used for a quadcopter.
Home-page: http://hardworkin-man.com:8080/scm/git/quadwi
Author: Mike Moore
Author-email: mickety.mike@gmail.com
License: MIT
Keywords: quadwi
Platform: UNKNOWN
Classifier: Development Status :: 3 - Alpha
Classifier: License :: OSI Approved :: MIT License
Classifier: Programming Language :: Python :: 2.7
Classifier: Topic :: Text Processing :: Linguistic
